batchtensor/__init__.py
batchtensor/constants.py
batchtensor/nested/__init__.py
batchtensor/nested/comparison.py
batchtensor/nested/conversion.py
batchtensor/nested/indexing.py
batchtensor/nested/joining.py
batchtensor/nested/math.py
batchtensor/nested/misc.py
batchtensor/nested/permutation.py
batchtensor/nested/pointwise.py
batchtensor/nested/reduction.py
batchtensor/nested/slicing.py
batchtensor/nested/trigo.py
batchtensor/recursive/__init__.py
batchtensor/recursive/auto.py
batchtensor/recursive/base.py
batchtensor/recursive/default.py
batchtensor/recursive/interface.py
batchtensor/recursive/mapping.py
batchtensor/recursive/sequence.py
batchtensor/recursive/state.py
batchtensor/tensor/__init__.py
batchtensor/tensor/comparison.py
batchtensor/tensor/indexing.py
batchtensor/tensor/joining.py
batchtensor/tensor/math.py
batchtensor/tensor/permutation.py
batchtensor/tensor/reduction.py
batchtensor/tensor/slicing.py
batchtensor/utils/__init__.py
batchtensor/utils/bfs.py
batchtensor/utils/dfs.py
batchtensor/utils/seed.py
batchtensor-0.1.0.dist-info/LICENSE
batchtensor-0.1.0.dist-info/METADATA
batchtensor-0.1.0.dist-info/WHEEL
batchtensor-0.1.0.dist-info/RECORD
