Metadata-Version: 2.3
Name: batchtensor
Version: 0.1.0
Summary: Functions to manipulate batches of PyTorch tensors
License: BSD-3-Clause
Keywords: batch,sequence,pytorch,tensor
Author: Thibaut Durand
Author-email: durand.tibo+gh@gmail.com
Requires-Python: >=3.9,<3.14
Classifier: Development Status :: 3 - Alpha
Classifier: Intended Audience :: Developers
Classifier: Intended Audience :: Information Technology
Classifier: Intended Audience :: Science/Research
Classifier: License :: OSI Approved :: BSD License
Classifier: Operating System :: POSIX :: Linux
Classifier: Programming Language :: Python :: 3
Classifier: Programming Language :: Python :: 3.9
Classifier: Programming Language :: Python :: 3.10
Classifier: Programming Language :: Python :: 3.11
Classifier: Programming Language :: Python :: 3.12
Classifier: Programming Language :: Python :: 3.13
Classifier: Topic :: Scientific/Engineering
Classifier: Topic :: Scientific/Engineering :: Artificial Intelligence
Classifier: Topic :: Software Development :: Libraries
Provides-Extra: all
Requires-Dist: coola (>=0.8.6,<1.0)
Requires-Dist: numpy (>=1.24,<3.0) ; extra == "all"
Requires-Dist: numpy (>=2.1,<3.0) ; (python_version == "3.13") and (extra == "all")
Requires-Dist: torch (>=2.4,<3.0)
Project-URL: Homepage, https://github.com/durandtibo/batchtensor
Project-URL: Repository, https://github.com/durandtibo/batchtensor
